odoo/addons/sale_disable_inventory_check/README.rst
odoo/addons/sale_disable_inventory_check/__init__.py
odoo/addons/sale_disable_inventory_check/__manifest__.py
odoo/addons/sale_disable_inventory_check/i18n/ca.po
odoo/addons/sale_disable_inventory_check/i18n/es.po
odoo/addons/sale_disable_inventory_check/i18n/sale_disable_inventory_check.pot
odoo/addons/sale_disable_inventory_check/i18n/sl.po
odoo/addons/sale_disable_inventory_check/i18n/tr.po
odoo/addons/sale_disable_inventory_check/models/__init__.py
odoo/addons/sale_disable_inventory_check/models/sale_order_line.py
odoo/addons/sale_disable_inventory_check/static/description/icon.png
odoo/addons/sale_disable_inventory_check/tests/__init__.py
odoo/addons/sale_disable_inventory_check/tests/test_disable_inventory_check.py
odoo12_addon_sale_disable_inventory_check-12.0.1.0.0.99.dev10.dist-info/METADATA
odoo12_addon_sale_disable_inventory_check-12.0.1.0.0.99.dev10.dist-info/WHEEL
odoo12_addon_sale_disable_inventory_check-12.0.1.0.0.99.dev10.dist-info/top_level.txt
odoo12_addon_sale_disable_inventory_check-12.0.1.0.0.99.dev10.dist-info/RECORD
